pdf_text_image_xtract/__init__.py
pdf_text_image_xtract/core.py
pdf_text_image_xtract/utils.py
pdf_text_image_xtract-0.1.0.dist-info/METADATA
pdf_text_image_xtract-0.1.0.dist-info/WHEEL
pdf_text_image_xtract-0.1.0.dist-info/top_level.txt
pdf_text_image_xtract-0.1.0.dist-info/RECORD
