Metadata-Version: 2.4
Name: pdf_text_image_xtract
Version: 0.1.0
Summary: A package for extracting images, texts and tables from pdfs
Author-email: Voldi Muyumba <voldi.muyumba@melio.ai>
Requires-Python: >=3.12
Requires-Dist: PyMuPDF<2.0,>=1.23
Requires-Dist: pdfplumber<1.0,>=0.11
Requires-Dist: boto3<2.0,>=1.33
Provides-Extra: dev
Requires-Dist: pytest>=8.0; extra == "dev"
